Nessus63ZhongwenYonghushouce/README.md
Nessus63ZhongwenYonghushouce/__init__.py
Nessus63ZhongwenYonghushouce/__main__.py
Nessus63ZhongwenYonghushouce/file.pdf
Nessus63ZhongwenYonghushouce/index.html
nessus_6_3_zhongwen_yonghushouce-2024.3.3.0.dist-info/METADATA
nessus_6_3_zhongwen_yonghushouce-2024.3.3.0.dist-info/WHEEL
nessus_6_3_zhongwen_yonghushouce-2024.3.3.0.dist-info/entry_points.txt
nessus_6_3_zhongwen_yonghushouce-2024.3.3.0.dist-info/top_level.txt
nessus_6_3_zhongwen_yonghushouce-2024.3.3.0.dist-info/RECORD
